LICENSE
MANIFEST.in
README.md
fdxprotocol.rst
fdxread
requirements.txt
setup.py
dumps/onsdagsregatta-2016-08-24.dump
fdxread.egg-info/PKG-INFO
fdxread.egg-info/SOURCES.txt
fdxread.egg-info/dependency_links.txt
fdxread.egg-info/requires.txt
fdxread.egg-info/top_level.txt
libfdx/__init__.py
libfdx/decode.py
libfdx/dumpreader.py
libfdx/dumpserial.py
libfdx/format_nmea.py
libfdx/formats.py
libfdx/interfaces.py
libfdx/pseudoserial.py