Metadata-Version: 1.1
Name: fdxread
Version: 0.9.1
Summary: An FDX protocol reader for Garmin GND10
Home-page: https://github.com/lkarsten/fdxread/
Author: Lasse Karstensen
Author-email: lasse.karstensen+pypi@gmail.com
License: GPLv2
Keywords: USB sailing boating nexus garmin GND10
Platform: UNKNOWN
Classifier: Development Status :: 4 - Beta
Classifier: Intended Audience :: End Users/Desktop
Classifier: License :: OSI Approved :: GNU General Public License v2 (GPLv2)
Classifier: Operating System :: MacOS :: MacOS X
Classifier: Operating System :: POSIX :: Linux
Classifier: Programming Language :: Python :: 2.7
Classifier: Programming Language :: Python :: 3.6
Classifier: Topic :: Scientific/Engineering :: Interface Engine/Protocol Translator
